nonebot_plugin_mongodb-0.1.0.dist-info/METADATA
nonebot_plugin_mongodb-0.1.0.dist-info/WHEEL
nonebot_plugin_mongodb-0.1.0.dist-info/licenses/LICENSE
nonebot_plugin_mongodb/__init__.py
nonebot_plugin_mongodb/config.py
nonebot_plugin_mongodb-0.1.0.dist-info/RECORD
