Metadata-Version: 2.1
Name: nonebot-plugin-mongodb
Version: 0.1.0
Summary: 基于 MongoDB ODM 的数据库管理插件
Author-Email: Well404 <well_404@outlook.com>
License: MIT
Requires-Python: >=3.8
Requires-Dist: nonebot2>=2.0.0
Requires-Dist: beanie>=1.20.0
Requires-Dist: nonebot-adapter-onebot>=2.2.3; extra == "dev"
Requires-Dist: nonebot2[fastapi,websockets]>=2.0.0; extra == "dev"
Provides-Extra: dev
